tracking_model/__init__.py
tracking_model/model.py
tracking_model/qp.py
tracking_model-0.2.0.dist-info/LICENSE
tracking_model-0.2.0.dist-info/WHEEL
tracking_model-0.2.0.dist-info/METADATA
tracking_model-0.2.0.dist-info/RECORD
