Metadata-Version: 2.1
Name: tracking-model
Version: 0.2.0
Summary: Genetic Algorithm Optimization for the Index-Tracking problem.
Author: Adriel Martins
Author-email: adrielfalcao@gmail.com
Requires-Python: >=3.8,<3.11
Classifier: Programming Language :: Python :: 3
Classifier: Programming Language :: Python :: 3.8
Classifier: Programming Language :: Python :: 3.9
Requires-Dist: cvxopt (>=1.2.6,<2.0.0)
Requires-Dist: numpy (>=1.21.2,<2.0.0)
Requires-Dist: pandas (>=1.3.2,<2.0.0)
